{"name": "Christy Morgan", "phone": "715-731-0381", "email": "christymorgan@jourrapide.com"}
{"name": "Joyce Bnight", "phone": "952-704-0267", "email": "sciales@jourrapide.com"}
{"name": "Margaret Morris", "phone": "413-229-2725", "email": "mmorris@dayrep.com"}
{"name": "Marsha Calkins", "phone": "231-813-1222", "email": "ccmarsha@rhyta.com"}
{"name": "Norman Edwards", "phone": "312-578-3429", "email": "heres1971@armyspy.com"}
{"name": "Rose Turnbull", "phone": "264-851-4442", "email": "turnbull_rose@rhyta.com"}
{"name": "Tyler Caldwell", "phone": "802-774-3634", "email": "datylercaldwell@armyspy.com"}
